ctflib/__init__.py
ctflib/crypto/__init__.py
ctflib/crypto/xor.py
ctflib/string/__init__.py
ctflib/string/consts.py
ctflib/string/random.py
ctflib-0.1.3.dist-info/METADATA
ctflib-0.1.3.dist-info/WHEEL
ctflib-0.1.3.dist-info/LICENSE
ctflib-0.1.3.dist-info/RECORD
