Metadata-Version: 2.1
Name: ctflib
Version: 0.1.3
Summary: Tools for better CTF experience
Home-page: https://github.com/LeKSuS-04/ctflib
License: WTFPL
Keywords: CTF
Author: Alexey Tarasov
Author-email: tarasovion2004@gmail.com
Requires-Python: >=3.10,<4.0
Classifier: Development Status :: 2 - Pre-Alpha
Classifier: License :: Other/Proprietary License
Classifier: Programming Language :: Python :: 3
Classifier: Programming Language :: Python :: 3.10
Classifier: Programming Language :: Python :: 3.11
Project-URL: Repository, https://github.com/LeKSuS-04/ctflib
